setup.py
Flask_ResponseFactory.egg-info/PKG-INFO
Flask_ResponseFactory.egg-info/SOURCES.txt
Flask_ResponseFactory.egg-info/dependency_links.txt
Flask_ResponseFactory.egg-info/not-zip-safe
Flask_ResponseFactory.egg-info/requires.txt
Flask_ResponseFactory.egg-info/top_level.txt
flask_responsefactory/__init__.py
flask_responsefactory/exceptions.py
flask_responsefactory/response.py
flask_responsefactory/status.py