Metadata-Version: 1.1
Name: Flask-ResponseFactory
Version: 0.1
Summary: Create Flask response objects in a declarative way
Home-page: https://github.com/joelcolucci/flask-responsefactory
Author: Joel Colucci
Author-email: joelcolucci@gmail.com
License: MIT
Platform: any
Classifier: Environment :: Web Environment
Classifier: Intended Audience :: Developers
Classifier: License :: OSI Approved :: MIT License
Classifier: Operating System :: OS Independent
Classifier: Programming Language :: Python
Classifier: Topic :: Internet :: WWW/HTTP :: Dynamic Content
Classifier: Topic :: Software Development :: Libraries :: Python Modules
